{"includedArchiveIdentifiers":["SwiftVisualization"],"interfaceLanguages":{"swift":[{"children":[{"title":"Classes","type":"groupMarker"},{"children":[{"title":"Initializers","type":"groupMarker"},{"path":"\/documentation\/swiftvisualization\/systemscsvparser\/init(delimiterbyte:quotebyte:)","title":"init(delimiterByte: UInt8, quoteByte: UInt8)","type":"init"},{"title":"Instance Methods","type":"groupMarker"},{"path":"\/documentation\/swiftvisualization\/systemscsvparser\/parse(buffer:)","title":"func parse(buffer: UnsafeBufferPointer<UInt8>) -> [[CSVFieldOffset]]","type":"method"}],"path":"\/documentation\/swiftvisualization\/systemscsvparser","title":"SystemsCSVParser","type":"class"},{"title":"Protocols","type":"groupMarker"},{"children":[{"title":"Instance Properties","type":"groupMarker"},{"path":"\/documentation\/swiftvisualization\/anycolumn\/count","title":"var count: Int","type":"property"},{"path":"\/documentation\/swiftvisualization\/anycolumn\/dtype","title":"var dtype: ColumnDType","type":"property"},{"path":"\/documentation\/swiftvisualization\/anycolumn\/name","title":"var name: String","type":"property"},{"path":"\/documentation\/swiftvisualization\/anycolumn\/nullcount","title":"var nullCount: Int","type":"property"},{"title":"Instance Methods","type":"groupMarker"},{"path":"\/documentation\/swiftvisualization\/anycolumn\/filtered(by:)","title":"func filtered(by: [Bool]) throws -> any AnyColumn","type":"method"},{"children":[{"title":"AnyColumn Implementations","type":"groupMarker"},{"path":"\/documentation\/swiftvisualization\/anycolumn\/filteredindices(matching:)-6a2o7","title":"func filteredIndices(matching: FilterCondition) -> [Int]?","type":"method"}],"path":"\/documentation\/swiftvisualization\/anycolumn\/filteredindices(matching:)","title":"func filteredIndices(matching: FilterCondition) -> [Int]?","type":"method"},{"path":"\/documentation\/swiftvisualization\/anycolumn\/gathered(at:)","title":"func gathered(at: [Int]) -> any AnyColumn","type":"method"},{"path":"\/documentation\/swiftvisualization\/anycolumn\/lagged(by:)","title":"func lagged(by: Int) -> any AnyColumn","type":"method"},{"path":"\/documentation\/swiftvisualization\/anycolumn\/renamed(to:)","title":"func renamed(to: String) -> any AnyColumn","type":"method"},{"path":"\/documentation\/swiftvisualization\/anycolumn\/sortedindices(ascending:)","title":"func sortedIndices(ascending: Bool) -> [Int]","type":"method"},{"path":"\/documentation\/swiftvisualization\/anycolumn\/todoubles()","title":"func toDoubles() -> [Double]?","type":"method"},{"path":"\/documentation\/swiftvisualization\/anycolumn\/tostrings()","title":"func toStrings() -> [String]","type":"method"},{"path":"\/documentation\/swiftvisualization\/anycolumn\/value(at:)","title":"func value(at: Int) -> Any?","type":"method"}],"path":"\/documentation\/swiftvisualization\/anycolumn","title":"AnyColumn","type":"protocol"},{"children":[{"title":"Instance Properties","type":"groupMarker"},{"path":"\/documentation\/swiftvisualization\/supportedtype\/doublevalue","title":"var doubleValue: Double?","type":"property"},{"title":"Type Properties","type":"groupMarker"},{"path":"\/documentation\/swiftvisualization\/supportedtype\/columndtype","title":"static var columnDType: ColumnDType","type":"property"},{"title":"Type Methods","type":"groupMarker"},{"path":"\/documentation\/swiftvisualization\/supportedtype\/parse(from:)","title":"static func parse(from: String) -> Self?","type":"method"}],"path":"\/documentation\/swiftvisualization\/supportedtype","title":"SupportedType","type":"protocol"},{"title":"Structures","type":"groupMarker"},{"children":[{"title":"Instance Properties","type":"groupMarker"},{"path":"\/documentation\/swiftvisualization\/anovaresult\/description","title":"var description: String","type":"property"},{"path":"\/documentation\/swiftvisualization\/anovaresult\/dfbetween","title":"let dfBetween: Int","type":"property"},{"path":"\/documentation\/swiftvisualization\/anovaresult\/dfwithin","title":"let dfWithin: Int","type":"property"},{"path":"\/documentation\/swiftvisualization\/anovaresult\/etasquared","title":"let etaSquared: Double","type":"property"},{"path":"\/documentation\/swiftvisualization\/anovaresult\/fstatistic","title":"let fStatistic: Double","type":"property"},{"path":"\/documentation\/swiftvisualization\/anovaresult\/issignificant","title":"var isSignificant: Bool","type":"property"},{"path":"\/documentation\/swiftvisualization\/anovaresult\/pvalue","title":"let pValue: Double","type":"property"}],"path":"\/documentation\/swiftvisualization\/anovaresult","title":"ANOVAResult","type":"struct"},{"children":[{"title":"Initializers","type":"groupMarker"},{"path":"\/documentation\/swiftvisualization\/csvfieldoffset\/init(startoffset:length:escapedquotespresent:)","title":"init(startOffset: Int, length: Int, escapedQuotesPresent: Bool)","type":"init"},{"title":"Instance Properties","type":"groupMarker"},{"path":"\/documentation\/swiftvisualization\/csvfieldoffset\/escapedquotespresent","title":"let escapedQuotesPresent: Bool","type":"property"},{"path":"\/documentation\/swiftvisualization\/csvfieldoffset\/length","title":"let length: Int","type":"property"},{"path":"\/documentation\/swiftvisualization\/csvfieldoffset\/startoffset","title":"let startOffset: Int","type":"property"}],"path":"\/documentation\/swiftvisualization\/csvfieldoffset","title":"CSVFieldOffset","type":"struct"},{"children":[{"title":"Initializers","type":"groupMarker"},{"path":"\/documentation\/swiftvisualization\/csvreadoptions\/init()","title":"init()","type":"init"},{"title":"Instance Properties","type":"groupMarker"},{"path":"\/documentation\/swiftvisualization\/csvreadoptions\/columntypeoverrides","title":"var columnTypeOverrides: [String : ColumnDType]","type":"property"},{"path":"\/documentation\/swiftvisualization\/csvreadoptions\/delimiter","title":"var delimiter: Character","type":"property"},{"path":"\/documentation\/swiftvisualization\/csvreadoptions\/hasheader","title":"var hasHeader: Bool","type":"property"},{"path":"\/documentation\/swiftvisualization\/csvreadoptions\/infertypes","title":"var inferTypes: Bool","type":"property"},{"path":"\/documentation\/swiftvisualization\/csvreadoptions\/maxrows","title":"var maxRows: Int?","type":"property"},{"path":"\/documentation\/swiftvisualization\/csvreadoptions\/nullvalues","title":"var nullValues: Set<String>","type":"property"},{"title":"Type Properties","type":"groupMarker"},{"path":"\/documentation\/swiftvisualization\/csvreadoptions\/default","title":"static let `default`: CSVReadOptions","type":"property"}],"path":"\/documentation\/swiftvisualization\/csvreadoptions","title":"CSVReadOptions","type":"struct"},{"children":[{"title":"Instance Properties","type":"groupMarker"},{"path":"\/documentation\/swiftvisualization\/chisquareresult\/degreesoffreedom","title":"let degreesOfFreedom: Int","type":"property"},{"path":"\/documentation\/swiftvisualization\/chisquareresult\/description","title":"var description: String","type":"property"},{"path":"\/documentation\/swiftvisualization\/chisquareresult\/issignificant","title":"var isSignificant: Bool","type":"property"},{"path":"\/documentation\/swiftvisualization\/chisquareresult\/pvalue","title":"let pValue: Double","type":"property"},{"path":"\/documentation\/swiftvisualization\/chisquareresult\/statistic","title":"let statistic: Double","type":"property"}],"path":"\/documentation\/swiftvisualization\/chisquareresult","title":"ChiSquareResult","type":"struct"},{"children":[{"title":"Instance Properties","type":"groupMarker"},{"path":"\/documentation\/swiftvisualization\/confidenceinterval\/confidence","title":"let confidence: Double","type":"property"},{"path":"\/documentation\/swiftvisualization\/confidenceinterval\/description","title":"var description: String","type":"property"},{"path":"\/documentation\/swiftvisualization\/confidenceinterval\/lower","title":"let lower: Double","type":"property"},{"path":"\/documentation\/swiftvisualization\/confidenceinterval\/upper","title":"let upper: Double","type":"property"}],"path":"\/documentation\/swiftvisualization\/confidenceinterval","title":"ConfidenceInterval","type":"struct"},{"children":[{"title":"Initializers","type":"groupMarker"},{"path":"\/documentation\/swiftvisualization\/dataframe\/init(arrowtable:)","title":"init(arrowTable: ArrowTable) throws","type":"init"},{"path":"\/documentation\/swiftvisualization\/dataframe\/init(columns:)","title":"init(columns: [any AnyColumn]) throws","type":"init"},{"path":"\/documentation\/swiftvisualization\/dataframe\/init(csv:options:)","title":"init(csv: URL, options: CSVReadOptions) async throws","type":"init"},{"path":"\/documentation\/swiftvisualization\/dataframe\/init(json:)","title":"init(json: URL) async throws","type":"init"},{"title":"Instance Properties","type":"groupMarker"},{"path":"\/documentation\/swiftvisualization\/dataframe\/columnnames","title":"var columnNames: [String]","type":"property"},{"path":"\/documentation\/swiftvisualization\/dataframe\/columns","title":"var columns: [any AnyColumn]","type":"property"},{"path":"\/documentation\/swiftvisualization\/dataframe\/dtypes","title":"var dtypes: [String : ColumnDType]","type":"property"},{"path":"\/documentation\/swiftvisualization\/dataframe\/shape","title":"var shape: (rows: Int, columns: Int)","type":"property"},{"title":"Instance Methods","type":"groupMarker"},{"path":"\/documentation\/swiftvisualization\/dataframe\/addcolumn(_:as:using:)","title":"func addColumn<T>(String, as: T.Type, using: (DataFrameRow) -> T?) throws -> DataFrame","type":"method"},{"path":"\/documentation\/swiftvisualization\/dataframe\/castcolumn(_:to:)","title":"func castColumn<T>(String, to: T.Type) throws -> DataFrame","type":"method"},{"path":"\/documentation\/swiftvisualization\/dataframe\/correlationmatrix()","title":"func correlationMatrix() throws -> DataFrame","type":"method"},{"path":"\/documentation\/swiftvisualization\/dataframe\/debugprint(maxrows:)","title":"func debugPrint(maxRows: Int)","type":"method"},{"path":"\/documentation\/swiftvisualization\/dataframe\/describe()","title":"func describe() throws -> DataFrame","type":"method"},{"path":"\/documentation\/swiftvisualization\/dataframe\/drop(_:)-em2t","title":"func drop(String...) throws -> DataFrame","type":"method"},{"path":"\/documentation\/swiftvisualization\/dataframe\/drop(_:)-v9s6","title":"func drop([String]) throws -> DataFrame","type":"method"},{"path":"\/documentation\/swiftvisualization\/dataframe\/filter(_:)","title":"func filter((DataFrameRow) -> Bool) -> DataFrame","type":"method"},{"path":"\/documentation\/swiftvisualization\/dataframe\/filter(column:where:)","title":"func filter(column: String, where: FilterCondition) throws -> DataFrame","type":"method"},{"path":"\/documentation\/swiftvisualization\/dataframe\/filterrows(by:)","title":"func filterRows(by: (Int) -> Bool) -> DataFrame","type":"method"},{"path":"\/documentation\/swiftvisualization\/dataframe\/gathered(at:)","title":"func gathered(at: [Int]) -> DataFrame","type":"method"},{"path":"\/documentation\/swiftvisualization\/dataframe\/groupby(_:)","title":"func groupBy(String...) -> GroupedDataFrame","type":"method"},{"path":"\/documentation\/swiftvisualization\/dataframe\/head(_:)","title":"func head(Int) -> DataFrame","type":"method"},{"path":"\/documentation\/swiftvisualization\/dataframe\/join(_:on:how:)","title":"func join(DataFrame, on: String, how: JoinKind) throws -> DataFrame","type":"method"},{"path":"\/documentation\/swiftvisualization\/dataframe\/melt(idvars:valuevars:varname:valuename:)","title":"func melt(idVars: [String], valueVars: [String], varName: String, valueName: String) throws -> DataFrame","type":"method"},{"path":"\/documentation\/swiftvisualization\/dataframe\/pivot(index:columns:values:aggfunc:)","title":"func pivot(index: String, columns: String, values: String, aggFunc: Aggregation) throws -> DataFrame","type":"method"},{"path":"\/documentation\/swiftvisualization\/dataframe\/renamecolumn(_:to:)","title":"func renameColumn(String, to: String) throws -> DataFrame","type":"method"},{"path":"\/documentation\/swiftvisualization\/dataframe\/row(at:)","title":"func row(at: Int) -> [String : Any?]","type":"method"},{"path":"\/documentation\/swiftvisualization\/dataframe\/sample(n:seed:ordered:)","title":"func sample(n: Int, seed: UInt64?, ordered: Bool) -> DataFrame","type":"method"},{"path":"\/documentation\/swiftvisualization\/dataframe\/schema()","title":"func schema() -> Schema","type":"method"},{"path":"\/documentation\/swiftvisualization\/dataframe\/select(_:)-1gp1r","title":"func select(String...) throws -> DataFrame","type":"method"},{"path":"\/documentation\/swiftvisualization\/dataframe\/select(_:)-1lp43","title":"func select([String]) throws -> DataFrame","type":"method"},{"path":"\/documentation\/swiftvisualization\/dataframe\/sortby(_:ascending:)","title":"func sortBy(String, ascending: Bool) throws -> DataFrame","type":"method"},{"path":"\/documentation\/swiftvisualization\/dataframe\/stats(for:)","title":"func stats(for: String) throws -> DescriptiveStats","type":"method"},{"path":"\/documentation\/swiftvisualization\/dataframe\/tail(_:)","title":"func tail(Int) -> DataFrame","type":"method"},{"path":"\/documentation\/swiftvisualization\/dataframe\/toarrowtable()","title":"func toArrowTable() throws -> ArrowTable","type":"method"},{"path":"\/documentation\/swiftvisualization\/dataframe\/tofeaturematrix(_:)","title":"func toFeatureMatrix([String]) throws -> [[Double]]","type":"method"},{"path":"\/documentation\/swiftvisualization\/dataframe\/totargetvector(_:)","title":"func toTargetVector(String) throws -> [Double]","type":"method"},{"path":"\/documentation\/swiftvisualization\/dataframe\/withcolumn(_:column:)","title":"func withColumn(String, column: any AnyColumn) throws -> DataFrame","type":"method"},{"path":"\/documentation\/swiftvisualization\/dataframe\/withlaggedcolumn(column:by:newname:)","title":"func withLaggedColumn(column: String, by: Int, newName: String) throws -> DataFrame","type":"method"},{"path":"\/documentation\/swiftvisualization\/dataframe\/writecsv(to:)","title":"func writeCSV(to: URL) async throws","type":"method"},{"title":"Subscripts","type":"groupMarker"},{"path":"\/documentation\/swiftvisualization\/dataframe\/subscript(column:)","title":"subscript(column _: String) -> (any AnyColumn)?","type":"subscript"},{"path":"\/documentation\/swiftvisualization\/dataframe\/subscript(column:as:)","title":"subscript<T>(column _: String, as _: T.Type) -> TypedColumn<T>?","type":"subscript"},{"title":"Type Properties","type":"groupMarker"},{"path":"\/documentation\/swiftvisualization\/dataframe\/empty","title":"static let empty: DataFrame","type":"property"},{"title":"Type Methods","type":"groupMarker"},{"path":"\/documentation\/swiftvisualization\/dataframe\/readcsvstream(contentsof:chunksize:options:)","title":"static func readCSVStream(contentsOf: URL, chunkSize: Int, options: CSVReadOptions) -> AsyncThrowingStream<DataFrame, any Error>","type":"method"}],"path":"\/documentation\/swiftvisualization\/dataframe","title":"DataFrame","type":"struct"},{"children":[{"title":"Instance Properties","type":"groupMarker"},{"path":"\/documentation\/swiftvisualization\/dataframerow\/columnnames","title":"let columnNames: [String]","type":"property"},{"title":"Instance Methods","type":"groupMarker"},{"path":"\/documentation\/swiftvisualization\/dataframerow\/isnull(column:)","title":"func isNull(column: String) -> Bool","type":"method"},{"path":"\/documentation\/swiftvisualization\/dataframerow\/value(column:as:)","title":"func value<T>(column: String, as: T.Type) -> T?","type":"method"},{"title":"Subscripts","type":"groupMarker"},{"path":"\/documentation\/swiftvisualization\/dataframerow\/subscript(_:)","title":"subscript(String) -> Any?","type":"subscript"}],"path":"\/documentation\/swiftvisualization\/dataframerow","title":"DataFrameRow","type":"struct"},{"children":[{"title":"Instance Properties","type":"groupMarker"},{"path":"\/documentation\/swiftvisualization\/descriptivestats\/count","title":"let count: Int","type":"property"},{"path":"\/documentation\/swiftvisualization\/descriptivestats\/description","title":"var description: String","type":"property"},{"path":"\/documentation\/swiftvisualization\/descriptivestats\/kurtosis","title":"let kurtosis: Double","type":"property"},{"path":"\/documentation\/swiftvisualization\/descriptivestats\/max","title":"let max: Double","type":"property"},{"path":"\/documentation\/swiftvisualization\/descriptivestats\/mean","title":"let mean: Double","type":"property"},{"path":"\/documentation\/swiftvisualization\/descriptivestats\/median","title":"let median: Double","type":"property"},{"path":"\/documentation\/swiftvisualization\/descriptivestats\/min","title":"let min: Double","type":"property"},{"path":"\/documentation\/swiftvisualization\/descriptivestats\/nullcount","title":"let nullCount: Int","type":"property"},{"path":"\/documentation\/swiftvisualization\/descriptivestats\/q1","title":"let q1: Double","type":"property"},{"path":"\/documentation\/swiftvisualization\/descriptivestats\/q3","title":"let q3: Double","type":"property"},{"path":"\/documentation\/swiftvisualization\/descriptivestats\/skewness","title":"let skewness: Double","type":"property"},{"path":"\/documentation\/swiftvisualization\/descriptivestats\/standarddeviation","title":"let standardDeviation: Double","type":"property"},{"path":"\/documentation\/swiftvisualization\/descriptivestats\/variance","title":"let variance: Double","type":"property"}],"path":"\/documentation\/swiftvisualization\/descriptivestats","title":"DescriptiveStats","type":"struct"},{"children":[{"title":"Instance Methods","type":"groupMarker"},{"path":"\/documentation\/swiftvisualization\/groupeddataframe\/agg(_:)","title":"func agg([String : Aggregation]) -> DataFrame","type":"method"},{"path":"\/documentation\/swiftvisualization\/groupeddataframe\/count()","title":"func count() -> DataFrame","type":"method"},{"path":"\/documentation\/swiftvisualization\/groupeddataframe\/max()","title":"func max() -> DataFrame","type":"method"},{"path":"\/documentation\/swiftvisualization\/groupeddataframe\/mean()","title":"func mean() -> DataFrame","type":"method"},{"path":"\/documentation\/swiftvisualization\/groupeddataframe\/min()","title":"func min() -> DataFrame","type":"method"},{"path":"\/documentation\/swiftvisualization\/groupeddataframe\/sum()","title":"func sum() -> DataFrame","type":"method"}],"path":"\/documentation\/swiftvisualization\/groupeddataframe","title":"GroupedDataFrame","type":"struct"},{"children":[{"title":"Instance Properties","type":"groupMarker"},{"path":"\/documentation\/swiftvisualization\/normalitytestresult\/description","title":"var description: String","type":"property"},{"path":"\/documentation\/swiftvisualization\/normalitytestresult\/isnormal","title":"var isNormal: Bool","type":"property"},{"path":"\/documentation\/swiftvisualization\/normalitytestresult\/pvalue","title":"let pValue: Double","type":"property"},{"path":"\/documentation\/swiftvisualization\/normalitytestresult\/statistic","title":"let statistic: Double","type":"property"}],"path":"\/documentation\/swiftvisualization\/normalitytestresult","title":"NormalityTestResult","type":"struct"},{"children":[{"title":"Structures","type":"groupMarker"},{"children":[{"title":"Initializers","type":"groupMarker"},{"path":"\/documentation\/swiftvisualization\/schema\/field\/init(name:dtype:nullable:)","title":"init(name: String, dtype: ColumnDType, nullable: Bool)","type":"init"},{"title":"Instance Properties","type":"groupMarker"},{"path":"\/documentation\/swiftvisualization\/schema\/field\/dtype","title":"let dtype: ColumnDType","type":"property"},{"path":"\/documentation\/swiftvisualization\/schema\/field\/name","title":"let name: String","type":"property"},{"path":"\/documentation\/swiftvisualization\/schema\/field\/nullable","title":"let nullable: Bool","type":"property"}],"path":"\/documentation\/swiftvisualization\/schema\/field","title":"Schema.Field","type":"struct"},{"title":"Initializers","type":"groupMarker"},{"path":"\/documentation\/swiftvisualization\/schema\/init(fields:)","title":"init(fields: [Schema.Field])","type":"init"},{"title":"Instance Properties","type":"groupMarker"},{"path":"\/documentation\/swiftvisualization\/schema\/columnnames","title":"var columnNames: [String]","type":"property"},{"path":"\/documentation\/swiftvisualization\/schema\/description","title":"var description: String","type":"property"},{"path":"\/documentation\/swiftvisualization\/schema\/dtypes","title":"var dtypes: [String : ColumnDType]","type":"property"},{"path":"\/documentation\/swiftvisualization\/schema\/fields","title":"let fields: [Schema.Field]","type":"property"},{"title":"Subscripts","type":"groupMarker"},{"path":"\/documentation\/swiftvisualization\/schema\/subscript(_:)","title":"subscript(String) -> Schema.Field?","type":"subscript"}],"path":"\/documentation\/swiftvisualization\/schema","title":"Schema","type":"struct"},{"children":[{"title":"Instance Properties","type":"groupMarker"},{"path":"\/documentation\/swiftvisualization\/ttestresult\/confidenceinterval","title":"let confidenceInterval: ConfidenceInterval","type":"property"},{"path":"\/documentation\/swiftvisualization\/ttestresult\/degreesoffreedom","title":"let degreesOfFreedom: Double","type":"property"},{"path":"\/documentation\/swiftvisualization\/ttestresult\/description","title":"var description: String","type":"property"},{"path":"\/documentation\/swiftvisualization\/ttestresult\/effectsize","title":"let effectSize: Double","type":"property"},{"path":"\/documentation\/swiftvisualization\/ttestresult\/issignificant","title":"var isSignificant: Bool","type":"property"},{"path":"\/documentation\/swiftvisualization\/ttestresult\/pvalue","title":"let pValue: Double","type":"property"},{"path":"\/documentation\/swiftvisualization\/ttestresult\/statistic","title":"let statistic: Double","type":"property"}],"path":"\/documentation\/swiftvisualization\/ttestresult","title":"TTestResult","type":"struct"},{"children":[{"title":"Initializers","type":"groupMarker"},{"path":"\/documentation\/swiftvisualization\/typedcolumn\/init(name:values:)","title":"init(name: String, values: [T?])","type":"init"},{"title":"Instance Properties","type":"groupMarker"},{"path":"\/documentation\/swiftvisualization\/typedcolumn\/count","title":"var count: Int","type":"property"},{"path":"\/documentation\/swiftvisualization\/typedcolumn\/dtype","title":"let dtype: ColumnDType","type":"property"},{"path":"\/documentation\/swiftvisualization\/typedcolumn\/name","title":"let name: String","type":"property"},{"path":"\/documentation\/swiftvisualization\/typedcolumn\/nonnullvalues","title":"var nonNullValues: [T]","type":"property"},{"path":"\/documentation\/swiftvisualization\/typedcolumn\/nullcount","title":"var nullCount: Int","type":"property"},{"path":"\/documentation\/swiftvisualization\/typedcolumn\/values","title":"let values: [T?]","type":"property"},{"title":"Instance Methods","type":"groupMarker"},{"path":"\/documentation\/swiftvisualization\/typedcolumn\/compactmap(_:)","title":"func compactMap<U>((T) -> U?) -> TypedColumn<U>","type":"method"},{"path":"\/documentation\/swiftvisualization\/typedcolumn\/dropnulls()","title":"func dropNulls() -> TypedColumn<T>","type":"method"},{"path":"\/documentation\/swiftvisualization\/typedcolumn\/fillnull(with:)","title":"func fillNull(with: T) -> TypedColumn<T>","type":"method"},{"path":"\/documentation\/swiftvisualization\/typedcolumn\/filtered(by:)","title":"func filtered(by: [Bool]) throws -> any AnyColumn","type":"method"},{"path":"\/documentation\/swiftvisualization\/typedcolumn\/filteredindices(matching:)","title":"func filteredIndices(matching: FilterCondition) -> [Int]?","type":"method"},{"path":"\/documentation\/swiftvisualization\/typedcolumn\/gathered(at:)","title":"func gathered(at: [Int]) -> any AnyColumn","type":"method"},{"path":"\/documentation\/swiftvisualization\/typedcolumn\/lagged(by:)","title":"func lagged(by: Int) -> any AnyColumn","type":"method"},{"path":"\/documentation\/swiftvisualization\/typedcolumn\/map(_:)","title":"func map<U>((T?) -> U?) -> TypedColumn<U>","type":"method"},{"path":"\/documentation\/swiftvisualization\/typedcolumn\/mean()","title":"func mean() -> Double","type":"method"},{"path":"\/documentation\/swiftvisualization\/typedcolumn\/renamed(to:)","title":"func renamed(to: String) -> any AnyColumn","type":"method"},{"path":"\/documentation\/swiftvisualization\/typedcolumn\/sortedindices(ascending:)","title":"func sortedIndices(ascending: Bool) -> [Int]","type":"method"},{"path":"\/documentation\/swiftvisualization\/typedcolumn\/stddev()","title":"func stdDev() -> Double","type":"method"},{"path":"\/documentation\/swiftvisualization\/typedcolumn\/todoubles()","title":"func toDoubles() -> [Double]?","type":"method"},{"path":"\/documentation\/swiftvisualization\/typedcolumn\/tostrings()","title":"func toStrings() -> [String]","type":"method"},{"path":"\/documentation\/swiftvisualization\/typedcolumn\/vgather(at:)","title":"func vGather(at: [Int]) -> TypedColumn<Double>","type":"method"},{"path":"\/documentation\/swiftvisualization\/typedcolumn\/value(at:)","title":"func value(at: Int) -> Any?","type":"method"},{"path":"\/documentation\/swiftvisualization\/typedcolumn\/variance()","title":"func variance() -> Double","type":"method"},{"title":"Subscripts","type":"groupMarker"},{"path":"\/documentation\/swiftvisualization\/typedcolumn\/subscript(_:)","title":"subscript(Int) -> T?","type":"subscript"},{"title":"Default Implementations","type":"groupMarker"},{"children":[{"title":"Operators","type":"groupMarker"},{"path":"\/documentation\/swiftvisualization\/typedcolumn\/!=(_:_:)","title":"static func != (borrowing Self, borrowing Self) -> Bool","type":"op"},{"path":"\/documentation\/swiftvisualization\/typedcolumn\/==(_:_:)","title":"static func == (TypedColumn<T>, TypedColumn<T>) -> Bool","type":"op"}],"path":"\/documentation\/swiftvisualization\/typedcolumn\/equatable-implementations","title":"Equatable Implementations","type":"collection"}],"path":"\/documentation\/swiftvisualization\/typedcolumn","title":"TypedColumn","type":"struct"},{"title":"Type Aliases","type":"groupMarker"},{"path":"\/documentation\/swiftvisualization\/clustererror","title":"ClusterError","type":"typealias"},{"path":"\/documentation\/swiftvisualization\/dataframeerror","title":"DataFrameError","type":"typealias"},{"path":"\/documentation\/swiftvisualization\/forecasterror","title":"ForecastError","type":"typealias"},{"path":"\/documentation\/swiftvisualization\/mlerror","title":"MLError","type":"typealias"},{"path":"\/documentation\/swiftvisualization\/nlperror","title":"NLPError","type":"typealias"},{"path":"\/documentation\/swiftvisualization\/preprocessingerror","title":"PreprocessingError","type":"typealias"},{"path":"\/documentation\/swiftvisualization\/statserror","title":"StatsError","type":"typealias"},{"title":"Enumerations","type":"groupMarker"},{"children":[{"title":"Enumeration Cases","type":"groupMarker"},{"path":"\/documentation\/swiftvisualization\/aggregation\/count","title":"case count","type":"case"},{"path":"\/documentation\/swiftvisualization\/aggregation\/first","title":"case first","type":"case"},{"path":"\/documentation\/swiftvisualization\/aggregation\/last","title":"case last","type":"case"},{"path":"\/documentation\/swiftvisualization\/aggregation\/max","title":"case max","type":"case"},{"path":"\/documentation\/swiftvisualization\/aggregation\/mean","title":"case mean","type":"case"},{"path":"\/documentation\/swiftvisualization\/aggregation\/min","title":"case min","type":"case"},{"path":"\/documentation\/swiftvisualization\/aggregation\/sum","title":"case sum","type":"case"},{"title":"Default Implementations","type":"groupMarker"},{"children":[{"title":"Operators","type":"groupMarker"},{"path":"\/documentation\/swiftvisualization\/aggregation\/!=(_:_:)","title":"static func != (borrowing Self, borrowing Self) -> Bool","type":"op"}],"path":"\/documentation\/swiftvisualization\/aggregation\/equatable-implementations","title":"Equatable Implementations","type":"collection"}],"path":"\/documentation\/swiftvisualization\/aggregation","title":"Aggregation","type":"enum"},{"children":[{"title":"Type Methods","type":"groupMarker"},{"path":"\/documentation\/swiftvisualization\/chartexporter\/plotconfusionmatrix(matrix:labels:title:)","title":"static func plotConfusionMatrix(matrix: [[Int]], labels: [String], title: String) -> String","type":"method"},{"path":"\/documentation\/swiftvisualization\/chartexporter\/plotcorrelationheatmap(df:title:)","title":"static func plotCorrelationHeatmap(df: DataFrame, title: String) throws -> String","type":"method"},{"path":"\/documentation\/swiftvisualization\/chartexporter\/plotfeatureimportances(featurenames:importances:title:)","title":"static func plotFeatureImportances(featureNames: [String], importances: [Double], title: String) -> String","type":"method"},{"path":"\/documentation\/swiftvisualization\/chartexporter\/plotroccurve(ytrue:yscores:title:)","title":"static func plotROCCurve(yTrue: [Int], yScores: [Double], title: String) -> String","type":"method"}],"path":"\/documentation\/swiftvisualization\/chartexporter","title":"ChartExporter","type":"enum"},{"children":[{"title":"Enumeration Cases","type":"groupMarker"},{"path":"\/documentation\/swiftvisualization\/columndtype\/boolean","title":"case boolean","type":"case"},{"path":"\/documentation\/swiftvisualization\/columndtype\/date32","title":"case date32","type":"case"},{"path":"\/documentation\/swiftvisualization\/columndtype\/float32","title":"case float32","type":"case"},{"path":"\/documentation\/swiftvisualization\/columndtype\/float64","title":"case float64","type":"case"},{"path":"\/documentation\/swiftvisualization\/columndtype\/int32","title":"case int32","type":"case"},{"path":"\/documentation\/swiftvisualization\/columndtype\/int64","title":"case int64","type":"case"},{"path":"\/documentation\/swiftvisualization\/columndtype\/utf8","title":"case utf8","type":"case"},{"title":"Instance Properties","type":"groupMarker"},{"path":"\/documentation\/swiftvisualization\/columndtype\/description","title":"var description: String","type":"property"},{"path":"\/documentation\/swiftvisualization\/columndtype\/isarithmetic","title":"var isArithmetic: Bool","type":"property"},{"path":"\/documentation\/swiftvisualization\/columndtype\/isnumeric","title":"var isNumeric: Bool","type":"property"},{"title":"Default Implementations","type":"groupMarker"},{"children":[{"title":"Operators","type":"groupMarker"},{"path":"\/documentation\/swiftvisualization\/columndtype\/!=(_:_:)","title":"static func != (borrowing Self, borrowing Self) -> Bool","type":"op"}],"path":"\/documentation\/swiftvisualization\/columndtype\/equatable-implementations","title":"Equatable Implementations","type":"collection"}],"path":"\/documentation\/swiftvisualization\/columndtype","title":"ColumnDType","type":"enum"},{"children":[{"title":"Enumeration Cases","type":"groupMarker"},{"path":"\/documentation\/swiftvisualization\/filtercondition\/contains(_:)","title":"case contains(String)","type":"case"},{"path":"\/documentation\/swiftvisualization\/filtercondition\/equals(_:)","title":"case equals(any Sendable)","type":"case"},{"path":"\/documentation\/swiftvisualization\/filtercondition\/greaterthan(_:)","title":"case greaterThan(any Sendable)","type":"case"},{"path":"\/documentation\/swiftvisualization\/filtercondition\/greaterthanorequal(_:)","title":"case greaterThanOrEqual(any Sendable)","type":"case"},{"path":"\/documentation\/swiftvisualization\/filtercondition\/isnotnull","title":"case isNotNull","type":"case"},{"path":"\/documentation\/swiftvisualization\/filtercondition\/isnull","title":"case isNull","type":"case"},{"path":"\/documentation\/swiftvisualization\/filtercondition\/lessthan(_:)","title":"case lessThan(any Sendable)","type":"case"},{"path":"\/documentation\/swiftvisualization\/filtercondition\/lessthanorequal(_:)","title":"case lessThanOrEqual(any Sendable)","type":"case"},{"path":"\/documentation\/swiftvisualization\/filtercondition\/notequals(_:)","title":"case notEquals(any Sendable)","type":"case"}],"path":"\/documentation\/swiftvisualization\/filtercondition","title":"FilterCondition","type":"enum"},{"children":[{"title":"Enumeration Cases","type":"groupMarker"},{"path":"\/documentation\/swiftvisualization\/joinkind\/inner","title":"case inner","type":"case"},{"path":"\/documentation\/swiftvisualization\/joinkind\/left","title":"case left","type":"case"},{"path":"\/documentation\/swiftvisualization\/joinkind\/outer","title":"case outer","type":"case"},{"path":"\/documentation\/swiftvisualization\/joinkind\/right","title":"case right","type":"case"},{"title":"Default Implementations","type":"groupMarker"},{"children":[{"title":"Operators","type":"groupMarker"},{"path":"\/documentation\/swiftvisualization\/joinkind\/!=(_:_:)","title":"static func != (borrowing Self, borrowing Self) -> Bool","type":"op"}],"path":"\/documentation\/swiftvisualization\/joinkind\/equatable-implementations","title":"Equatable Implementations","type":"collection"}],"path":"\/documentation\/swiftvisualization\/joinkind","title":"JoinKind","type":"enum"},{"children":[{"title":"Enumeration Cases","type":"groupMarker"},{"path":"\/documentation\/swiftvisualization\/normorder\/infinity","title":"case infinity","type":"case"},{"path":"\/documentation\/swiftvisualization\/normorder\/l1","title":"case l1","type":"case"},{"path":"\/documentation\/swiftvisualization\/normorder\/l2","title":"case l2","type":"case"},{"title":"Default Implementations","type":"groupMarker"},{"children":[{"title":"Operators","type":"groupMarker"},{"path":"\/documentation\/swiftvisualization\/normorder\/!=(_:_:)","title":"static func != (borrowing Self, borrowing Self) -> Bool","type":"op"}],"path":"\/documentation\/swiftvisualization\/normorder\/equatable-implementations","title":"Equatable Implementations","type":"collection"}],"path":"\/documentation\/swiftvisualization\/normorder","title":"NormOrder","type":"enum"},{"children":[{"title":"Type Methods","type":"groupMarker"},{"path":"\/documentation\/swiftvisualization\/stats\/add(_:_:)","title":"static func add([Double], [Double]) throws -> [Double]","type":"method"},{"path":"\/documentation\/swiftvisualization\/stats\/chisquaregoodnessoffit(observed:expected:)","title":"static func chiSquareGoodnessOfFit(observed: [Double], expected: [Double]) throws -> ChiSquareResult","type":"method"},{"path":"\/documentation\/swiftvisualization\/stats\/correlationmatrix(_:)","title":"static func correlationMatrix([[Double]]) throws -> [[Double]]","type":"method"},{"path":"\/documentation\/swiftvisualization\/stats\/cosinesimilarity(_:_:)","title":"static func cosineSimilarity([Double], [Double]) throws -> Double","type":"method"},{"path":"\/documentation\/swiftvisualization\/stats\/covariance(_:_:ddof:)","title":"static func covariance([Double], [Double], ddof: Int) throws -> Double","type":"method"},{"path":"\/documentation\/swiftvisualization\/stats\/describe(_:nullcount:checknan:)","title":"static func describe([Double], nullCount: Int, checkNaN: Bool) throws -> DescriptiveStats","type":"method"},{"path":"\/documentation\/swiftvisualization\/stats\/dotproduct(_:_:)","title":"static func dotProduct([Double], [Double]) throws -> Double","type":"method"},{"path":"\/documentation\/swiftvisualization\/stats\/kolmogorovsmirnov(_:)","title":"static func kolmogorovSmirnov([Double]) throws -> NormalityTestResult","type":"method"},{"path":"\/documentation\/swiftvisualization\/stats\/kurtosis(_:checknan:)","title":"static func kurtosis([Double], checkNaN: Bool) throws -> Double","type":"method"},{"path":"\/documentation\/swiftvisualization\/stats\/max(_:)","title":"static func max([Double]) throws -> Double","type":"method"},{"path":"\/documentation\/swiftvisualization\/stats\/mean(_:)","title":"static func mean([Float]) throws -> Float","type":"method"},{"path":"\/documentation\/swiftvisualization\/stats\/mean(_:checknan:)","title":"static func mean([Double], checkNaN: Bool) throws -> Double","type":"method"},{"path":"\/documentation\/swiftvisualization\/stats\/median(_:checknan:)","title":"static func median([Double], checkNaN: Bool) throws -> Double","type":"method"},{"path":"\/documentation\/swiftvisualization\/stats\/min(_:)","title":"static func min([Double]) throws -> Double","type":"method"},{"path":"\/documentation\/swiftvisualization\/stats\/mode(_:)","title":"static func mode([Double]) throws -> [Double]","type":"method"},{"path":"\/documentation\/swiftvisualization\/stats\/norm(_:order:)","title":"static func norm([Double], order: NormOrder) throws -> Double","type":"method"},{"path":"\/documentation\/swiftvisualization\/stats\/normalise(_:)","title":"static func normalise([Double]) throws -> [Double]","type":"method"},{"path":"\/documentation\/swiftvisualization\/stats\/onewayanova(groups:)","title":"static func oneWayANOVA(groups: [[Double]]) throws -> ANOVAResult","type":"method"},{"path":"\/documentation\/swiftvisualization\/stats\/pairedttest(before:after:)","title":"static func pairedTTest(before: [Double], after: [Double]) throws -> TTestResult","type":"method"},{"path":"\/documentation\/swiftvisualization\/stats\/pearsoncorrelation(_:_:)","title":"static func pearsonCorrelation([Double], [Double]) throws -> Double","type":"method"},{"path":"\/documentation\/swiftvisualization\/stats\/percentile(_:q:checknan:)","title":"static func percentile([Double], q: Double, checkNaN: Bool) throws -> Double","type":"method"},{"path":"\/documentation\/swiftvisualization\/stats\/quantiles(_:probs:checknan:)","title":"static func quantiles([Double], probs: [Double], checkNaN: Bool) throws -> [Double]","type":"method"},{"path":"\/documentation\/swiftvisualization\/stats\/range(_:)","title":"static func range([Double]) throws -> Double","type":"method"},{"path":"\/documentation\/swiftvisualization\/stats\/scale(_:by:)","title":"static func scale([Double], by: Double) -> [Double]","type":"method"},{"path":"\/documentation\/swiftvisualization\/stats\/shapirowilk(_:)","title":"static func shapiroWilk([Double]) throws -> NormalityTestResult","type":"method"},{"path":"\/documentation\/swiftvisualization\/stats\/skewness(_:checknan:)","title":"static func skewness([Double], checkNaN: Bool) throws -> Double","type":"method"},{"path":"\/documentation\/swiftvisualization\/stats\/spearmancorrelation(_:_:)","title":"static func spearmanCorrelation([Double], [Double]) throws -> Double","type":"method"},{"path":"\/documentation\/swiftvisualization\/stats\/standarddeviation(_:ddof:checknan:)","title":"static func standardDeviation([Double], ddof: Int, checkNaN: Bool) throws -> Double","type":"method"},{"path":"\/documentation\/swiftvisualization\/stats\/standardise(_:)","title":"static func standardise([Double]) throws -> [Double]","type":"method"},{"path":"\/documentation\/swiftvisualization\/stats\/subtract(_:_:)","title":"static func subtract([Double], [Double]) throws -> [Double]","type":"method"},{"path":"\/documentation\/swiftvisualization\/stats\/sum(_:)","title":"static func sum([Double]) throws -> Double","type":"method"},{"path":"\/documentation\/swiftvisualization\/stats\/ttest(sample1:sample2:equalvariances:)","title":"static func tTest(sample1: [Double], sample2: [Double], equalVariances: Bool) throws -> TTestResult","type":"method"},{"path":"\/documentation\/swiftvisualization\/stats\/ttest(sample:populationmean:)","title":"static func tTest(sample: [Double], populationMean: Double) throws -> TTestResult","type":"method"},{"path":"\/documentation\/swiftvisualization\/stats\/variance(_:ddof:checknan:)","title":"static func variance([Double], ddof: Int, checkNaN: Bool) throws -> Double","type":"method"}],"path":"\/documentation\/swiftvisualization\/stats","title":"Stats","type":"enum"},{"children":[{"title":"Enumeration Cases","type":"groupMarker"},{"path":"\/documentation\/swiftvisualization\/swiftmlerror\/castfailed(column:targettype:)","title":"case castFailed(column: String, targetType: String)","type":"case"},{"path":"\/documentation\/swiftvisualization\/swiftmlerror\/columnlengthmismatch(expected:got:column:)","title":"case columnLengthMismatch(expected: Int, got: Int, column: String)","type":"case"},{"path":"\/documentation\/swiftvisualization\/swiftmlerror\/columnnotfound(_:)","title":"case columnNotFound(String)","type":"case"},{"path":"\/documentation\/swiftvisualization\/swiftmlerror\/constantcolumn(index:)","title":"case constantColumn(index: Int)","type":"case"},{"path":"\/documentation\/swiftvisualization\/swiftmlerror\/containsinfinity","title":"case containsInfinity","type":"case"},{"path":"\/documentation\/swiftvisualization\/swiftmlerror\/containsnan","title":"case containsNaN","type":"case"},{"path":"\/documentation\/swiftvisualization\/swiftmlerror\/convergencefailed(iterations:)","title":"case convergenceFailed(iterations: Int)","type":"case"},{"path":"\/documentation\/swiftvisualization\/swiftmlerror\/dimensionmismatch(expected:got:)","title":"case dimensionMismatch(expected: Int, got: Int)","type":"case"},{"path":"\/documentation\/swiftvisualization\/swiftmlerror\/divisionbyzero(context:)","title":"case divisionByZero(context: String)","type":"case"},{"path":"\/documentation\/swiftvisualization\/swiftmlerror\/duplicatecolumnname(_:)","title":"case duplicateColumnName(String)","type":"case"},{"path":"\/documentation\/swiftvisualization\/swiftmlerror\/emptydataframe(operation:)","title":"case emptyDataFrame(operation: String)","type":"case"},{"path":"\/documentation\/swiftvisualization\/swiftmlerror\/emptyinput","title":"case emptyInput","type":"case"},{"path":"\/documentation\/swiftvisualization\/swiftmlerror\/emptyschema","title":"case emptySchema","type":"case"},{"path":"\/documentation\/swiftvisualization\/swiftmlerror\/emptytimeseries","title":"case emptyTimeSeries","type":"case"},{"path":"\/documentation\/swiftvisualization\/swiftmlerror\/filenotfound(_:)","title":"case fileNotFound(URL)","type":"case"},{"path":"\/documentation\/swiftvisualization\/swiftmlerror\/indexoutofrange(index:count:)","title":"case indexOutOfRange(index: Int, count: Int)","type":"case"},{"path":"\/documentation\/swiftvisualization\/swiftmlerror\/insufficientdata(minimum:got:)","title":"case insufficientData(minimum: Int, got: Int)","type":"case"},{"path":"\/documentation\/swiftvisualization\/swiftmlerror\/insufficientlength(minimum:got:)","title":"case insufficientLength(minimum: Int, got: Int)","type":"case"},{"path":"\/documentation\/swiftvisualization\/swiftmlerror\/invalidarorder(_:)","title":"case invalidAROrder(Int)","type":"case"},{"path":"\/documentation\/swiftvisualization\/swiftmlerror\/invalidalpha(_:)","title":"case invalidAlpha(Double)","type":"case"},{"path":"\/documentation\/swiftvisualization\/swiftmlerror\/invalidbeta(_:)","title":"case invalidBeta(Double)","type":"case"},{"path":"\/documentation\/swiftvisualization\/swiftmlerror\/invalidddof(_:)","title":"case invalidDDOF(Int)","type":"case"},{"path":"\/documentation\/swiftvisualization\/swiftmlerror\/invaliddifferencing(_:)","title":"case invalidDifferencing(Int)","type":"case"},{"path":"\/documentation\/swiftvisualization\/swiftmlerror\/invalidgamma(_:)","title":"case invalidGamma(Double)","type":"case"},{"path":"\/documentation\/swiftvisualization\/swiftmlerror\/invalidgroupcount(minimum:got:)","title":"case invalidGroupCount(minimum: Int, got: Int)","type":"case"},{"path":"\/documentation\/swiftvisualization\/swiftmlerror\/invalidhorizon(_:)","title":"case invalidHorizon(Int)","type":"case"},{"path":"\/documentation\/swiftvisualization\/swiftmlerror\/invalidinput(_:)","title":"case invalidInput(String)","type":"case"},{"path":"\/documentation\/swiftvisualization\/swiftmlerror\/invalidmaorder(_:)","title":"case invalidMAOrder(Int)","type":"case"},{"path":"\/documentation\/swiftvisualization\/swiftmlerror\/invalidparameter(_:)","title":"case invalidParameter(String)","type":"case"},{"path":"\/documentation\/swiftvisualization\/swiftmlerror\/invalidpercentile(_:)","title":"case invalidPercentile(Double)","type":"case"},{"path":"\/documentation\/swiftvisualization\/swiftmlerror\/invalidperiod(_:)","title":"case invalidPeriod(Int)","type":"case"},{"path":"\/documentation\/swiftvisualization\/swiftmlerror\/invalidsamplesize(requested:available:)","title":"case invalidSampleSize(requested: Int, available: Int)","type":"case"},{"path":"\/documentation\/swiftvisualization\/swiftmlerror\/invalidseasonalperiod(_:)","title":"case invalidSeasonalPeriod(Int)","type":"case"},{"path":"\/documentation\/swiftvisualization\/swiftmlerror\/invalidvocabulary","title":"case invalidVocabulary","type":"case"},{"path":"\/documentation\/swiftvisualization\/swiftmlerror\/matrixdimensionmismatch(expectedrows:expectedcols:gotrows:gotcols:)","title":"case matrixDimensionMismatch(expectedRows: Int, expectedCols: Int, gotRows: Int, gotCols: Int)","type":"case"},{"path":"\/documentation\/swiftvisualization\/swiftmlerror\/modelnotfitted","title":"case modelNotFitted","type":"case"},{"path":"\/documentation\/swiftvisualization\/swiftmlerror\/negativevariance","title":"case negativeVariance","type":"case"},{"path":"\/documentation\/swiftvisualization\/swiftmlerror\/parseerror(line:description:)","title":"case parseError(line: Int, description: String)","type":"case"},{"path":"\/documentation\/swiftvisualization\/swiftmlerror\/partialcastfailure(column:targettype:failed:total:)","title":"case partialCastFailure(column: String, targetType: String, failed: Int, total: Int)","type":"case"},{"path":"\/documentation\/swiftvisualization\/swiftmlerror\/singularmatrix","title":"case singularMatrix","type":"case"},{"path":"\/documentation\/swiftvisualization\/swiftmlerror\/sizemismatch(sizea:sizeb:)","title":"case sizeMismatch(sizeA: Int, sizeB: Int)","type":"case"},{"path":"\/documentation\/swiftvisualization\/swiftmlerror\/svdfailed(info:)","title":"case svdFailed(info: Int32)","type":"case"},{"path":"\/documentation\/swiftvisualization\/swiftmlerror\/toomanysamples(limit:got:)","title":"case tooManySamples(limit: Int, got: Int)","type":"case"},{"path":"\/documentation\/swiftvisualization\/swiftmlerror\/trainingfailed(_:)","title":"case trainingFailed(String)","type":"case"},{"path":"\/documentation\/swiftvisualization\/swiftmlerror\/typemismatch(column:expected:got:)","title":"case typeMismatch(column: String, expected: String, got: String)","type":"case"},{"path":"\/documentation\/swiftvisualization\/swiftmlerror\/unknowncategory(_:)","title":"case unknownCategory(String)","type":"case"},{"path":"\/documentation\/swiftvisualization\/swiftmlerror\/unsupportedformat(_:)","title":"case unsupportedFormat(String)","type":"case"},{"path":"\/documentation\/swiftvisualization\/swiftmlerror\/unsupportedoperation(_:)","title":"case unsupportedOperation(String)","type":"case"},{"path":"\/documentation\/swiftvisualization\/swiftmlerror\/writeerror(_:)","title":"case writeError(String)","type":"case"},{"title":"Instance Properties","type":"groupMarker"},{"path":"\/documentation\/swiftvisualization\/swiftmlerror\/description","title":"var description: String","type":"property"},{"path":"\/documentation\/swiftvisualization\/swiftmlerror\/errordescription","title":"var errorDescription: String?","type":"property"},{"title":"Type Properties","type":"groupMarker"},{"path":"\/documentation\/swiftvisualization\/swiftmlerror\/fitnotcalled","title":"static var fitNotCalled: SwiftMLError","type":"property"},{"path":"\/documentation\/swiftvisualization\/swiftmlerror\/fittingrequired","title":"static var fittingRequired: SwiftMLError","type":"property"},{"path":"\/documentation\/swiftvisualization\/swiftmlerror\/notfitted","title":"static var notFitted: SwiftMLError","type":"property"},{"title":"Default Implementations","type":"groupMarker"},{"children":[{"title":"Operators","type":"groupMarker"},{"path":"\/documentation\/swiftvisualization\/swiftmlerror\/!=(_:_:)","title":"static func != (borrowing Self, borrowing Self) -> Bool","type":"op"}],"path":"\/documentation\/swiftvisualization\/swiftmlerror\/equatable-implementations","title":"Equatable Implementations","type":"collection"},{"children":[{"title":"Instance Properties","type":"groupMarker"},{"path":"\/documentation\/swiftvisualization\/swiftmlerror\/localizeddescription","title":"var localizedDescription: String","type":"property"}],"path":"\/documentation\/swiftvisualization\/swiftmlerror\/error-implementations","title":"Error Implementations","type":"collection"},{"children":[{"title":"Instance Properties","type":"groupMarker"},{"path":"\/documentation\/swiftvisualization\/swiftmlerror\/failurereason","title":"var failureReason: String?","type":"property"},{"path":"\/documentation\/swiftvisualization\/swiftmlerror\/helpanchor","title":"var helpAnchor: String?","type":"property"},{"path":"\/documentation\/swiftvisualization\/swiftmlerror\/recoverysuggestion","title":"var recoverySuggestion: String?","type":"property"}],"path":"\/documentation\/swiftvisualization\/swiftmlerror\/localizederror-implementations","title":"LocalizedError Implementations","type":"collection"}],"path":"\/documentation\/swiftvisualization\/swiftmlerror","title":"SwiftMLError","type":"enum"},{"children":[{"title":"Type Methods","type":"groupMarker"},{"path":"\/documentation\/swiftvisualization\/vectorizedbyteparsers\/parsedouble(buffer:offset:)","title":"static func parseDouble(buffer: UnsafeBufferPointer<UInt8>, offset: CSVFieldOffset) -> Double?","type":"method"},{"path":"\/documentation\/swiftvisualization\/vectorizedbyteparsers\/parseint(buffer:offset:)","title":"static func parseInt(buffer: UnsafeBufferPointer<UInt8>, offset: CSVFieldOffset) -> Int?","type":"method"},{"path":"\/documentation\/swiftvisualization\/vectorizedbyteparsers\/parsestring(buffer:offset:)","title":"static func parseString(buffer: UnsafeBufferPointer<UInt8>, offset: CSVFieldOffset) -> String","type":"method"}],"path":"\/documentation\/swiftvisualization\/vectorizedbyteparsers","title":"VectorizedByteParsers","type":"enum"},{"title":"Extended Modules","type":"groupMarker"},{"children":[{"title":"Extended Structures","type":"groupMarker"},{"children":[{"title":"Default Implementations","type":"groupMarker"},{"children":[{"title":"Instance Properties","type":"groupMarker"},{"path":"\/documentation\/swiftvisualization\/foundation\/date\/doublevalue","title":"var doubleValue: Double?","type":"property"},{"title":"Type Properties","type":"groupMarker"},{"path":"\/documentation\/swiftvisualization\/foundation\/date\/columndtype","title":"static var columnDType: ColumnDType","type":"property"},{"title":"Type Methods","type":"groupMarker"},{"path":"\/documentation\/swiftvisualization\/foundation\/date\/parse(from:)","title":"static func parse(from: String) -> Date?","type":"method"}],"path":"\/documentation\/swiftvisualization\/foundation\/date\/supportedtype-implementations","title":"SupportedType Implementations","type":"collection"}],"path":"\/documentation\/swiftvisualization\/foundation\/date","title":"Date","type":"extension"}],"path":"\/documentation\/swiftvisualization\/foundation","title":"Foundation","type":"extension"},{"children":[{"title":"Extended Structures","type":"groupMarker"},{"children":[{"title":"Default Implementations","type":"groupMarker"},{"children":[{"title":"Instance Properties","type":"groupMarker"},{"path":"\/documentation\/swiftvisualization\/swift\/bool\/doublevalue","title":"var doubleValue: Double?","type":"property"},{"title":"Type Properties","type":"groupMarker"},{"path":"\/documentation\/swiftvisualization\/swift\/bool\/columndtype","title":"static var columnDType: ColumnDType","type":"property"},{"title":"Type Methods","type":"groupMarker"},{"path":"\/documentation\/swiftvisualization\/swift\/bool\/parse(from:)","title":"static func parse(from: String) -> Bool?","type":"method"}],"path":"\/documentation\/swiftvisualization\/swift\/bool\/supportedtype-implementations","title":"SupportedType Implementations","type":"collection"}],"path":"\/documentation\/swiftvisualization\/swift\/bool","title":"Bool","type":"extension"},{"children":[{"title":"Default Implementations","type":"groupMarker"},{"children":[{"title":"Instance Properties","type":"groupMarker"},{"path":"\/documentation\/swiftvisualization\/swift\/double\/doublevalue","title":"var doubleValue: Double?","type":"property"},{"title":"Type Properties","type":"groupMarker"},{"path":"\/documentation\/swiftvisualization\/swift\/double\/columndtype","title":"static var columnDType: ColumnDType","type":"property"},{"title":"Type Methods","type":"groupMarker"},{"path":"\/documentation\/swiftvisualization\/swift\/double\/parse(from:)","title":"static func parse(from: String) -> Double?","type":"method"}],"path":"\/documentation\/swiftvisualization\/swift\/double\/supportedtype-implementations","title":"SupportedType Implementations","type":"collection"}],"path":"\/documentation\/swiftvisualization\/swift\/double","title":"Double","type":"extension"},{"children":[{"title":"Default Implementations","type":"groupMarker"},{"children":[{"title":"Instance Properties","type":"groupMarker"},{"path":"\/documentation\/swiftvisualization\/swift\/float\/doublevalue","title":"var doubleValue: Double?","type":"property"},{"title":"Type Properties","type":"groupMarker"},{"path":"\/documentation\/swiftvisualization\/swift\/float\/columndtype","title":"static var columnDType: ColumnDType","type":"property"},{"title":"Type Methods","type":"groupMarker"},{"path":"\/documentation\/swiftvisualization\/swift\/float\/parse(from:)","title":"static func parse(from: String) -> Float?","type":"method"}],"path":"\/documentation\/swiftvisualization\/swift\/float\/supportedtype-implementations","title":"SupportedType Implementations","type":"collection"}],"path":"\/documentation\/swiftvisualization\/swift\/float","title":"Float","type":"extension"},{"children":[{"title":"Default Implementations","type":"groupMarker"},{"children":[{"title":"Instance Properties","type":"groupMarker"},{"path":"\/documentation\/swiftvisualization\/swift\/int\/doublevalue","title":"var doubleValue: Double?","type":"property"},{"title":"Type Properties","type":"groupMarker"},{"path":"\/documentation\/swiftvisualization\/swift\/int\/columndtype","title":"static var columnDType: ColumnDType","type":"property"},{"title":"Type Methods","type":"groupMarker"},{"path":"\/documentation\/swiftvisualization\/swift\/int\/parse(from:)","title":"static func parse(from: String) -> Int?","type":"method"}],"path":"\/documentation\/swiftvisualization\/swift\/int\/supportedtype-implementations","title":"SupportedType Implementations","type":"collection"}],"path":"\/documentation\/swiftvisualization\/swift\/int","title":"Int","type":"extension"},{"children":[{"title":"Default Implementations","type":"groupMarker"},{"children":[{"title":"Instance Properties","type":"groupMarker"},{"path":"\/documentation\/swiftvisualization\/swift\/int32\/doublevalue","title":"var doubleValue: Double?","type":"property"},{"title":"Type Properties","type":"groupMarker"},{"path":"\/documentation\/swiftvisualization\/swift\/int32\/columndtype","title":"static var columnDType: ColumnDType","type":"property"},{"title":"Type Methods","type":"groupMarker"},{"path":"\/documentation\/swiftvisualization\/swift\/int32\/parse(from:)","title":"static func parse(from: String) -> Int32?","type":"method"}],"path":"\/documentation\/swiftvisualization\/swift\/int32\/supportedtype-implementations","title":"SupportedType Implementations","type":"collection"}],"path":"\/documentation\/swiftvisualization\/swift\/int32","title":"Int32","type":"extension"},{"children":[{"title":"Default Implementations","type":"groupMarker"},{"children":[{"title":"Instance Properties","type":"groupMarker"},{"path":"\/documentation\/swiftvisualization\/swift\/int64\/doublevalue","title":"var doubleValue: Double?","type":"property"},{"title":"Type Properties","type":"groupMarker"},{"path":"\/documentation\/swiftvisualization\/swift\/int64\/columndtype","title":"static var columnDType: ColumnDType","type":"property"},{"title":"Type Methods","type":"groupMarker"},{"path":"\/documentation\/swiftvisualization\/swift\/int64\/parse(from:)","title":"static func parse(from: String) -> Int64?","type":"method"}],"path":"\/documentation\/swiftvisualization\/swift\/int64\/supportedtype-implementations","title":"SupportedType Implementations","type":"collection"}],"path":"\/documentation\/swiftvisualization\/swift\/int64","title":"Int64","type":"extension"},{"children":[{"title":"Default Implementations","type":"groupMarker"},{"children":[{"title":"Instance Properties","type":"groupMarker"},{"path":"\/documentation\/swiftvisualization\/swift\/string\/doublevalue","title":"var doubleValue: Double?","type":"property"},{"title":"Type Properties","type":"groupMarker"},{"path":"\/documentation\/swiftvisualization\/swift\/string\/columndtype","title":"static var columnDType: ColumnDType","type":"property"},{"title":"Type Methods","type":"groupMarker"},{"path":"\/documentation\/swiftvisualization\/swift\/string\/parse(from:)","title":"static func parse(from: String) -> String?","type":"method"}],"path":"\/documentation\/swiftvisualization\/swift\/string\/supportedtype-implementations","title":"SupportedType Implementations","type":"collection"}],"path":"\/documentation\/swiftvisualization\/swift\/string","title":"String","type":"extension"}],"path":"\/documentation\/swiftvisualization\/swift","title":"Swift","type":"extension"}],"path":"\/documentation\/swiftvisualization","title":"SwiftVisualization","type":"module"}]},"schemaVersion":{"major":0,"minor":1,"patch":2}}